biocomp/__init__.py
biocomp/biocomp.py
biocomp/biograph.py
biocomp/fungi.py
biocomp/physarum.py
biocomp-0.2.4.dist-info/LICENSE
biocomp-0.2.4.dist-info/METADATA
biocomp-0.2.4.dist-info/WHEEL
biocomp-0.2.4.dist-info/entry_points.txt
biocomp-0.2.4.dist-info/top_level.txt
biocomp-0.2.4.dist-info/RECORD
