Metadata-Version: 2.1
Name: biocomp
Version: 0.2.4
Summary: BioComp  'Coded Life' to propozycja języka domenowo-specyficznego (DSL) do edukacji i wdrażania biocomputingu 
Home-page: https://www.biokomputer.pl
Author: Tom Sapletta
Author-email: info@softreck.dev
Classifier: Development Status :: 3 - Alpha
Classifier: Intended Audience :: Developers
Classifier: License :: OSI Approved :: Apache Software License
Classifier: Operating System :: OS Independent
Classifier: Programming Language :: Python :: 3
Classifier: Programming Language :: Python :: 3.6
Classifier: Programming Language :: Python :: 3.7
Classifier: Programming Language :: Python :: 3.8
Classifier: Programming Language :: Python :: 3.9
License-File: LICENSE
